setup.py
hamper/__init__.py
hamper/acl.py
hamper/cli.py
hamper/commander.py
hamper/config.py
hamper/interfaces.py
hamper/log.py
hamper/utils.py
hamper.egg-info/PKG-INFO
hamper.egg-info/SOURCES.txt
hamper.egg-info/dependency_links.txt
hamper.egg-info/entry_points.txt
hamper.egg-info/requires.txt
hamper.egg-info/top_level.txt
hamper/plugins/__init__.py
hamper/plugins/bitly.py
hamper/plugins/channel_utils.py
hamper/plugins/commands.py
hamper/plugins/dictionary.py
hamper/plugins/factoids.py
hamper/plugins/flip.py
hamper/plugins/friendly.py
hamper/plugins/goodbye.py
hamper/plugins/help.py
hamper/plugins/karma.py
hamper/plugins/plugin_utils.py
hamper/plugins/questions.py
hamper/plugins/quotes.py
hamper/plugins/roulette.py
hamper/plugins/seen.py
hamper/plugins/suggest.py
hamper/plugins/timez.py
hamper/plugins/tinyurl.py
hamper/plugins/whatwasthat.py
hamper/tests/__init__.py
hamper/tests/test_command.py
hamper/tests/test_interfaces.py
hamper/tests/test_permissions.py