Metadata-Version: 1.0
Name: hamper
Version: 1.8.1
Summary: Yet another IRC bot
Home-page: https://www.github.com/hamperbot/hamper
Author: Mike Cooper
Author-email: mythmon@gmail.com
License: UNKNOWN
Platform: UNKNOWN
